atflow/__init__.py
atflow/constraints.py
atflow/dataset.py
atflow/display.py
atflow/gitlogger.py
atflow/losses.py
atflow/misc.py
atflow/network.py
atflow/regularizers.py
atflow/trainers.py
atflow/version.py
atflow-0.0.3.dist-info/DESCRIPTION.rst
atflow-0.0.3.dist-info/METADATA
atflow-0.0.3.dist-info/RECORD
atflow-0.0.3.dist-info/WHEEL
atflow-0.0.3.dist-info/metadata.json
atflow-0.0.3.dist-info/top_level.txt
