Metadata-Version: 2.0
Name: atflow
Version: 0.0.3
Summary: TensorFlow library for Andreas Tolias lab
Home-page: https://github.com/atlab/atflow
Author: Edgar Y. Walker
Author-email: edgar.walker@gmail.com
License: GNU LGPL
Keywords: tensorflow
Platform: UNKNOWN
Classifier: Development Status :: 4 - Beta
Classifier: Intended Audience :: Science/Research
Classifier: Programming Language :: Python :: 3 :: Only
Requires-Dist: numpy
